symlib/__init__.py
symlib/file_management.py
symlib/lib.py
symlib/match.py
symlib/sampling.py
symlib/star_tagging.py
symlib/util.py
symlib/validate.py
symlib-1.5.0.dist-info/LICENSE
symlib-1.5.0.dist-info/METADATA
symlib-1.5.0.dist-info/WHEEL
symlib-1.5.0.dist-info/top_level.txt
symlib-1.5.0.dist-info/RECORD
