Metadata-Version: 2.1
Name: symlib
Version: 1.5.0
Summary: A library for working with data from the Symphony and MW-est zoom-in suites.
Home-page: https://github.com/phil-mansfield/symlib
Author: Philip Mansfield
Author-email: mansfield.astro@gmail.com
License: UNKNOWN
Keywords: python
Platform: UNKNOWN
Classifier: Programming Language :: Python :: 3
Classifier: License :: OSI Approved :: MIT License
Classifier: Operating System :: OS Independent
Requires-Python: >=3.6
License-File: LICENSE
Requires-Dist: numpy
Requires-Dist: scipy
Requires-Dist: matplotlib
Requires-Dist: colossus
Requires-Dist: requests
